dataporter/__init__.py
dataporter/csv2file.py
dataporter/csv2sql.py
dataporter/sql2csv.py
dataporter/sql_schema2txt.py
dataporter/utils.py
dataporter-0.1.8.dist-info/METADATA
dataporter-0.1.8.dist-info/WHEEL
dataporter-0.1.8.dist-info/entry_points.txt
dataporter-0.1.8.dist-info/RECORD
