Metadata-Version: 2.1
Name: dataporter
Version: 0.1.8
Summary: convert csv to csv/json/sql or convert sql to csv
Author: AuthorPlaceholder
Requires-Python: >=3.10,<4.0
Classifier: Programming Language :: Python :: 3
Classifier: Programming Language :: Python :: 3.10
Classifier: Programming Language :: Python :: 3.11
Requires-Dist: cryptography (>=40.0.2,<41.0.0)
Requires-Dist: fire (>=0.5.0,<0.6.0)
Requires-Dist: loguru (>=0.7.0,<0.8.0)
Requires-Dist: pandas (>=2.0.1,<2.1.0)
Requires-Dist: pymysql (>=1.0.3,<2.0.0)
Requires-Dist: sqlalchemy (>=2.0.13,<3.0.0)
